LICENSE.txt
README.md
setup.cfg
setup.py
nft_sha_maker/__init__.py
nft_sha_maker/__main__.py
nft_sha_maker/nft_sha_maker.py
nft_sha_maker.egg-info/PKG-INFO
nft_sha_maker.egg-info/SOURCES.txt
nft_sha_maker.egg-info/dependency_links.txt
nft_sha_maker.egg-info/entry_points.txt
nft_sha_maker.egg-info/top_level.txt